Metadata-Version: 2.1
Name: awsPrint
Version: 1.3
Summary: colorful print
Home-page: https://github.com/Gorkor227/awsPrint
Author: Gorkor
Author-email: 2226750760@qq.com
Maintainer: Gorkor
Maintainer-email: 2226750760@qq.com
License: MIT License
Classifier: Development Status :: 3 - Alpha
Classifier: Intended Audience :: Developers
Classifier: Topic :: Software Development :: Build Tools
Classifier: License :: OSI Approved :: MIT License
Classifier: Programming Language :: Python :: 3
Requires-Python: >=3
